django_jsonforms/__init__.py
django_jsonforms/apps.py
django_jsonforms/forms.py
django_jsonforms/static/django_jsonforms/jsoneditor_init.js
django_jsonforms/templates/django_jsonforms/jsoneditor.html
django_jsonforms/tests/__init__.py
django_jsonforms/tests/tests.py
django_jsonforms/tests/testapp/__init__.py
django_jsonforms/tests/testapp/settings.py
django_jsonforms/tests/testapp/urls.py
django_jsonforms/tests/testapp/views.py
django_jsonforms-1.1.2.dist-info/LICENSE.txt
django_jsonforms-1.1.2.dist-info/METADATA
django_jsonforms-1.1.2.dist-info/WHEEL
django_jsonforms-1.1.2.dist-info/top_level.txt
django_jsonforms-1.1.2.dist-info/RECORD
