Metadata-Version: 2.1
Name: django-jsonforms
Version: 1.1.2
Summary: JSON Schema forms for Django
Home-page: https://github.com/Aristotle-Metadata-Enterprises/django-jsonforms
Author: Harry White
Author-email: UNKNOWN
License: BSD
Platform: UNKNOWN
Requires-Dist: jsonschema
Requires-Dist: django (>=2.0)
